setup.py
mnubo/__init__.py
mnubo/api_manager.py
mnubo/mnubo_client.py
mnubo/services.py
mnubo.egg-info/PKG-INFO
mnubo.egg-info/SOURCES.txt
mnubo.egg-info/dependency_links.txt
mnubo.egg-info/requires.txt
mnubo.egg-info/top_level.txt