Metadata-Version: 1.0
Name: mnubo
Version: 0.2.0
Summary: Python SDK to access mnubo ingestion APIs
Home-page: https://github.com/mnubo/mnubo-python-sdk
Author: mnubo
Author-email: sos@mnubo.com
License: UNKNOWN
Keywords: mnubo,api,sdk,iot,smartobject
Platform: UNKNOWN
